setup.py
sprocket/__init__.py
sprocket/auth.py
sprocket/base_resource.py
sprocket/django_model_resource.py
sprocket/fields.py
sprocket/mixins.py
sprocket/utils.py
sprocket.egg-info/PKG-INFO
sprocket.egg-info/SOURCES.txt
sprocket.egg-info/dependency_links.txt
sprocket.egg-info/requires.txt
sprocket.egg-info/top_level.txt
sprocket/test/__init__.py
sprocket/test/settings_for_tests.py
sprocket/test/test_base_resource.py
sprocket/test/test_django_model_resource.py