Metadata-Version: 1.0
Name: sprocket
Version: 0.1
Summary: Web API organization with Mixins.
Home-page:  http://hubspot.com/
Author: Patrick Fitzsimmons
Author-email: pfitzsimmons@hubspot.com
License: UNKNOWN
Platform: any
